PyControl/continous.py
PyControl/fmin.py
PyControl/helpers.py
PyControl/plotter.py
PyControl/symbolic.py
PyControl/time_response.py
pyControlToolbox-0.2.2.dist-info/LICENSE
pyControlToolbox-0.2.2.dist-info/METADATA
pyControlToolbox-0.2.2.dist-info/WHEEL
pyControlToolbox-0.2.2.dist-info/top_level.txt
pyControlToolbox-0.2.2.dist-info/RECORD
