Metadata-Version: 2.1
Name: pyControlToolbox
Version: 0.2.2
Summary: Package for simulation and design of control systems
Home-page: https://github.com/btcHehe/PyControl
Author: Bartosz Czaja
Author-email: btc121314@gmail.com
License: UNKNOWN
Project-URL: Bug Tracker, https://github.com/btcHehe/PyControl/issues
Platform: UNKNOWN
Classifier: Development Status :: 2 - Pre-Alpha
Classifier: Programming Language :: Python :: 3
Classifier: License :: OSI Approved :: GNU General Public License v3 (GPLv3)
Classifier: Programming Language :: Python :: 3
Classifier: Operating System :: OS Independent
License-File: LICENSE
